mlx_lm_utils.py
mlx_lm_utils-0.0.4.dist-info/LICENSE
mlx_lm_utils-0.0.4.dist-info/METADATA
mlx_lm_utils-0.0.4.dist-info/WHEEL
mlx_lm_utils-0.0.4.dist-info/top_level.txt
mlx_lm_utils-0.0.4.dist-info/RECORD
