Metadata-Version: 2.2
Name: mlx-lm-utils
Version: 0.0.4
Summary: MLX-LM utils
Home-page: https://github.com/JosefAlbers/mlx-lm-utils
Author: Josef Albers
Author-email: albersj66@gmail.com
License: MIT
Requires-Python: >=3.12.8
License-File: LICENSE
Requires-Dist: mlx-lm==0.21.4
Dynamic: author
Dynamic: author-email
Dynamic: description
Dynamic: description-content-type
Dynamic: home-page
Dynamic: license
Dynamic: requires-dist
Dynamic: requires-python
Dynamic: summary
